{
  "gtk2": [
    {
      "desktopName": "lxde",
      "desktopTitle": "LXDE",
      "generalInfo": {
        "desktopCategory": "lightweight",
        "desktopGithubURL": "n/a",
        "desktopHomepage": "https://lxde.org/",
        "distrosFeature": "Lubuntu, LXLE"
      },
      "install": {
        "arch": "sudo pacman -S lxde-common lxsession",
        "fedora": "",
        "opensuse": {
          "reference": "<a href=\"https://en.opensuse.org/LXDE_repositories\">LXDE Repos for Suse</a>",
          "repoLeap15": "",
          "repoleap153": "",
          "twRepo": ""
        },
        "ubuntu": {
          "ubuntuInstall": "sudo apt install lxde"
        }
      },
      "requirements": {
        "reqHDDSpace": "6GB Minimum",
        "reqMemory": "1GB",
        "reqProcessor": "512Mhz or faster; 32bit or 64bit"
      },
      "screenshots": {
        "distro": "LXLE",
        "src": "ubuntu/lxle.png",
        "thumbnail": "ubuntu/thumbnails/lxle_tn.png"
      },
      "versions": {
        "arch": "0.99.2-2",
        "debian": {
          "busterVersion": "10",
          "bullseyeVersion": "11",
          "bookwormVersion": "11",
          "sidVersion": "11"
        },
        "fedora": {
          "f33": "",
          "f34": "",
          "f35": "", 
          "rawhide": ""
        },
        "latestVersion": "11",
        "opensuse": {
          "leap152": "",
          "leap153": "",
          "tumbleweed": ""
        },
        "solus": "N/A",
        "ubuntu": {
          "bionic": "10",
          "focal": "10",
          "impish": "11",
          "mint": {
            "mint20": "N/A",
            "mint19": "N/A"
          },
          "neonversion": "N/A"
        },
        "updated": "November 30, 2018"
      }
    }
  ],
  "gtk3": [
    {
      "desktopName": "cinnamon",
      "desktopTitle": "Cinnamon",
      "generalInfo": {
        "desktopCategory": "heavyweight",
        "desktopGithubURL": "https://github.com/linuxmint/cinnamon-desktop",
        "desktopHomepage": "https://github.com/linuxmint/cinnamon-desktop",
        "distrosFeature": "Linux Mint, Fedora, Arch"
      },
      "install": {
        "arch": "sudo pacman -S cinnamon",
        "fedora": "sudo dnf groupinstall cinnamon-desktop",
        "opensuse": {
          "opensuseInstall": "(See instructions for each branch, below)",
          "reference": "<a href=\"https://en.opensuse.org/Portal:Cinnamon\"target=\"_blank\"> Install Cinnamon on OpenSuse </a>",
          "repoLeap15": "# zypper ar -qry http://download.opensuse.org/repositories/X11:/Cinnamon:/Current/openSUSE_Leap_15.0/X11:Cinnamon:Current.repo <br /> # zypper ref && zypper in -t pattern cinnamon",
          "repoleap153": "# zypper ar -qry http://download.opensuse.org/repositories/X11:/Cinnamon:/Current/openSUSE_Leap_15.1/X11:Cinnamon:Current.repo <br /># zypper ref && zypper in -t pattern cinnamon",
          "twRepo": "zypper ref && zypper in -y cinnamon cinnamon-screensaver"
        },
        "ubuntu": {
          "mintInstall": "sudo apt install mint-meta-cinnamon",
          "ubuntuInstall": "PPA Needed - Info coming later"
        }
      },
      "requirements": {
        "reqHDDSpace": "10GB (Min)",
        "reqMemory": "1GB Recommended (Xmetal's comment:I would say 2GB to 4GB for COMFORTABLE usage)",
        "reqProcessor": "32bit or 64bit processor (Xmetal Comment:I'd say dual-core ... about from 2009 on should be ok for LOWEST I'd recommend"
      },
      "screenshots": {
        "distro": "Linux Mint",
        "icon": "Mint-X",
        "src": "ubuntu/cinnamonMint.png",
        "theme": "Mint-X",
        "thumbnail": "ubuntu/thumbnails/cinnamonMint_tn.png"
      },
      "versions": {
        "arch": "5.0.6-1",
        "debian": {
          "bullseye": "4.8.6-2",
          "buster": "3.8.8-1",
          "bookworm": "5.0.5-2",
          "sid": "5.0.5-2"
        },
        "fedora": {
          "f33": "4.8.6-5",
          "f34": "5.0.6-1",
          "f35": "",
          "rawhide": ""
        },
        "latestVersion": "",
        "opensuse": {
          "leap152": "4.4.8-1",
          "leap153": "4.6.7-1",
          "tumbleweed": "5.0.5-1.2"
        },
        "solus": "N/A",
        "ubuntu": {
          "bionic": "3.6.7-8",
          "focal": "4.4.8-4",
          "impish": "4.4.8-4",
          "mint": {
            "mint20": "",
            "mint19": ""
          },
          "neonversion": "n/a"
        },
        "updated": "Oct 16, 2021"
      }
    },
    {
      "desktopName": "budgie",
      "desktopTitle": "Budgie",
      "generalInfo": {
        "desktopCategory": "",
        "desktopGithubURL": "https://github.com/solus-project/budgie-desktop",
        "desktopHomepage": "https://budgie-desktop.org/home/",
        "distrosFeature": "Solus, Ubuntu Budgie"
      },
      "install": {
        "arch": "sudo pacman -S budgie-desktop",
        "fedora": "",
        "opensuse": {
          "opensuseInstall": "",
          "reference": "",
          "repoLeap15": "",
          "repoleap153": "",
          "twRepo": ""
        },
        "ubuntu": {
          "mintInstall": "",
          "ubuntuInstall": "sudo apt install budgie-desktop"
        }
      },
      "requirements": {
        "reqHDDSpace": "",
        "reqMemory": "",
        "reqProcessor": ""
      },
      "screenshots": {
        "distro": "Solus",
        "src": "solus/solusbudgie.png",
        "thumbnail": "solus/thumbnails/solusbudgie_tn.png"
      },
      "versions": {
        "arch": "10.5.3-1",
        "debian": {
          "bullseye": "10.5.2-4",
          "buster": "10.5-1",
          "bookworm": "10.5.3-2",
          "sid": "10.5.3-4"
        },
        "fedora": {
          "f33": "Unofficial Repos - https://software.opensuse.org/package/budgie-desktop",
          "f34": "Unofficial Repos - https://software.opensuse.org/package/budgie-desktop",
          "f35": "N/A",
          "rawhide": "Unofficial Repos - https://software.opensuse.org/package/budgie-desktop"
        },
        "latestVersion": "10.5.2",
        "opensuse": {
          "leap152": "10.5.1+1",
          "leap153": "10.5.1+1",
          "tumbleweed": "10.5.1-6"
        },
        "solus": "10.5.2",
        "ubuntu": {
          "bionic": "10.4*",
          "focal": "10.5.1-6",
          "impish": "10.5.1-6",
          "mint": {
            "mint20": "N/A",
            "mint19": "N/A"
          },
          "neonversion": "N/A"
        },
        "updated": "Oct 16, 2021"
      }
    },
    {
      "desktopName": "mate",
      "desktopTitle": "Mate",
      "generalInfo": {
        "desktopCategory": "lightweight",
        "desktopGithubURL": "https://github.com/mate-desktop",
        "desktopHomepage": "https://mate-desktop.org/",
        "distrosFeature": "Ubuntu Mate, Linux Mint Mate, Fedora, Arch/Antergos"
      },
      "install": {
        "arch": "sudo pacman -S mate mate-extra",
        "fedora": "sudo dnf groupinstall mate-desktop mate-applications",
        "opensuse": {
          "reference": "https://en.opensuse.org/Portal:MATE/Install",
          "twrepo": "zypper ar -r http://download.opensuse.org/repositories/X11:/MATE:/Current/openSUSE_Tumbleweed/X11:MATE:Current.repo"
        },
        "ubuntu": {
          "mintinstall": "sudo apt install mint-meta-mate",
          "ubuntuInstall": "sudo apt install mate-desktop-environment"
        }
      },
      "requirements": {
        "reqHDDSpace": "",
        "reqMemory": "",
        "reqProcessor": ""
      },
      "screenshots": {
        "distro": "Ubuntu Mate",
        "src": "ubuntu/umate1.png",
        "thumbnail": "ubuntu/thumbnails/umate1_tn.png"
      },
      "versions": {
        "arch": "1.26.0-1",
        "debian": {
          "bullseyeVersion": "1.24.0+4",
          "busterVersion": "1.20.0+5",
          "bookwormVersion": "1.24.0+4",
          "sidVersion": "1.24.0+4"
        },
        "fedora": {
          "f33": "1.24.1-4",
          "f34": "1.26.0-1",
          "f35": "",
          "rawhide": ""
        },
        "latestVersion": "1.26.0",
        "opensuse": {
          "leap152": "1.24.0-1",
          "leap153": "1.24.0-1",
          "tumbleweed": "1.26.0-1.3"
        },
        "solus": "1.24",
        "ubuntu": {
          "bionic": "1.20.1-2",
          "focal": "1.24.0-2",
          "impish": "1.24.0-2",
          "mint": {
            "mint20": "1.24.x",
            "mint19": "1.22.2"
          },
          "neonversion": "N/A"
        },
        "updated": "Oct 16, 2021"
      }
    },
    {
      "desktopName": "gnome",
      "desktopTitle": "Gnome Shell",
      "generalInfo": {
        "desktopCategory": "heavyweight",
        "desktopGithubURL": "",
        "desktopHomepage": "https://www.gnome.org/",
        "distrosFeature": "Ubuntu, Fedora, Solus, OpenSuse"
      },
      "install": {
        "arch": "",
        "fedora": "",
        "opensuse": {
          "reference": "",
          "twrepo": ""
        },
        "ubuntu": {
          "mintinstall": "",
          "ubuntuInstall": ""
        }
      },
      "requirements": {
        "reqHDDSpace": "",
        "reqMemory": "",
        "reqProcessor": ""
      },
      "screenshots": {
        "distro": "Ubuntu 20.10 (settings)",
        "src": "ubuntu/ubuntu2010settings.png",
        "thumbnail": "ubuntu/thumbnails/ubuntu2010settings_tn.png"
      },
      "versions": {
        "arch": "40.4-1",
        "debian": {
          "busterVersion": "3.30+1",
          "bullseyeVersion": "3.38+3",
          "bookwormVersion": "40+1",
          "sidVersion": "40+1"
        },
        "fedora": {
          "f33": "3.38.x",
          "f34": "40.x",
          "f35": "41.x",
          "rawhide": "41.x"
        },
        "latestVersion": "41.x",
        "opensuse": {
          "leap152": "",
          "leap153": "3.34.5",
          "tumbleweed": "41"
        },
        "solus": "(Solus 4.3) 40.2",
        "ubuntu": {
          "bionic": "3.28.2",
          "focal": "3.36.1-1",
          "impish": "40.4-2",
          "mint": {
            "mint20": "N/A",
            "mint19": "N/A"
          },
          "neonversion": "N/A"
        },
        "updated": "Oct 16, 2021"
      }
    },
    {
      "desktopName": "xfce",
      "desktopTitle": "XFCE",
      "generalInfo": {
        "desktopCategory": "lightweight",
        "desktopGithubURL": "n/a",
        "desktopHomepage": "https://xfce.org/",
        "distrosFeature": "mintHP . 'Manjaro XFCE, Manjaro by MM, Xubuntu, SoyldX, Uberstudent"
      },
      "install": {
        "arch": "sudo pacman -S xfce4 xfce-goodies",
        "fedora": "sudo dnf groupinstall xfce-desktop",
        "opensuse": {
          "reference": "",
          "repoLeap15": "",
          "repoleap153": "",
          "twRepo": ""
        },
        "ubuntu": {
          "mintInstall": "",
          "ubuntuInstall": "sudo apt install xfce xfce-goodies"
        }
      },
      "requirements": {
        "reqHDDSpace": "",
        "reqMemory": "",
        "reqProcessor": ""
      },
      "screenshots": {
        "distro": "Linux Lite",
        "src": "ubuntu/linuxlite.png",
        "thumbnail": "ubuntu/thumbnails/linuxlite_tn.png"
      },
      "ubuntu": {
        "install": "sudo apt install xfce4 xfce4-goodies",
        "mintinstall": "sudo apt install mint-meta-xfce",
        "neonversion": ""
      },
      "versions": {
        "arch": "4.16.1-1",
        "fedora": {
          "f33": "",
          "f34": "",
          "f35": "",
          "rawhide": "4.16"
        },
        "latestVersion": "4.16",
        "opensuse": {
          "leap152": "4.14.3",
          "leap153": "4.16",
          "tumbleweed": "4.16.2"
        },
        "solus": "N/A",
        "ubuntu": {
          "bionic": "4.12.4",
          "focal": "",
          "mint": {
            "mint20": "",
            "mint19": ""
          }
        },
        "updated": ""
      }
    }
  ],
  "qt": [
    {
      "desktopName": "plasma5",
      "desktopTitle": "Plasma 5",
      "generalInfo": {
        "desktopCategory": "heavyweight",
        "desktopGithubURL": "",
        "desktopHomepage": "https://kde.org/announcements/",
        "distrosFeature": "Kubuntu, KDE Neon, Arch, OpenSuse, Fedora"
      },
      "install": {
        "arch": "sudo pacman -S kde OR sudo pacman kde-meta",
        "fedora": "sudo dnf group install kde-desktop-environment",
        "opensuse": {
          "install": "sudo zypper in -t pattern kde kde_plasma"
        },
        "ubuntu": {
          "install": "sudo apt install plasma-desktop",
          "mintinstall": "(Mint prior to version 19) sudo apt (or apt-get) install mint-meta-kde"
        }
      },
      "requirements": {
        "reqHDDSpace": "",
        "reqMemory": "",
        "reqProcessor": ""
      },
      "screenshots": {
        "distro": "Kubuntu 20.04",
        "src": "ubuntu/kubuntu.png",
        "thumbnail": "ubuntu/thumbnails/kubuntu_tn.png"
      },
      "versions": {
        "arch": "5.23.0-2",
        "debian": {
          "bullseyeVersion": "5.20.5-4",
          "busterVersion": "5.14.5.1-1",
          "bookwormVersion": "5.21.5-2",
          "sidVersion": "5.23.0-3"
        },
        "fedora": {
          "f33": "5.20.5-1",
          "f34": "5.22.5-1",
          "f35": "",
          "rawhide": ""
        },
        "latestVersion": "",
        "opensuse": {
          "leap152": "",
          "leap153": "",
          "tumbleweed": ""
        },
        "solus": "(Solus 4.2 Release) Plasma Desktop 5.20.5, KDE Frameworks 5.78, KDE Applications 20.12.1 and QT 5.15.2",
        "ubuntu": {
          "bionic": "5.12.4-0",
          "focal": "5.18.4.1-0",
          "impish": "5.18.4.1-0",
          "mint": {
            "mint20": "",
            "mint19": ""
          },
          "neonversion": "5.10.4"
        },
        "updated": "Oct 16, 2021"
      }
    },
    {
      "desktopName": "lxqt",
      "desktopTitle": "LXQT",
      "generalInfo": {
        "desktopCategory": "Light",
        "desktopHomepage": "https://lxqt.org/",
        "distrosFeature": "Lubuntu Next, Sparky Linux"
      },
      "install": {
        "arch": "",
        "fedora": "",
        "opensuse": {
          "reference": "",
          "repoLeap15": "",
          "repoTW": "",
          "repoleap153": ""
        },
        "ubuntu": "sudo apt install lxqt"
      },
      "requirements": {
        "reqHDDSpace": "",
        "reqMemory": "",
        "reqProcessor": ""
      },
      "screenshots": {
        "distro": "Lubuntu 18.10",
        "src": "ubuntu/lubuntu.png",
        "thumbnail": "ubuntu/thumbnails/lubuntu_tn.png"
      },
      "versions": {
        "arch": "",
        "fedora": {
          "f32": "",
          "rawhide": ""
        },
        "latestVersion": "0.13.0",
        "opensuse": {
          "leap152": "",
          "leap153": "",
          "tumbleweed": ""
        },
        "solus": "N/A",
        "ubuntu": {
          "bionic": "",
          "focal": "",
          "mint": {
            "mint20": "",
            "mint19": ""
          }
        },
        "updated": ""
      }
    }
  ],
  "wm": [
    {
      "desktopName": "openbox",
      "desktopTitle": "Openbox",
      "generalInfo": {
        "desktopCategory": "Light",
        "desktopHomepage": "",
        "distrosFeature": "Crunchbang++, Bunsenlabs, Arch"
      },
      "install": {
        "arch": "sudo pacman -S openbox",
        "fedora": "",
        "mintinstall": "",
        "opensuse": "",
        "ubuntu": "sudo apt install openbox"
      },
      "requirements": {
        "reqHDDSpace": "",
        "reqMemory": "",
        "reqProcessor": ""
      },
      "screenshots": {
        "distro": "Bunsenlabs",
        "src": "debian/bunsenlabs.png",
        "thumbnail": "debian/thumbnails/bunsenlabs_tn.png"
      },
      "versions": {
        "arch": "",
        "debian": {
          "busterVersion": "3.6.1-8",
          "bullseyeVersion": "3.6.1-9",
          "bookwormVersion": "3.6.1-9",
          "sidVersion": "3.6.1-9"
        },
        "fedora": {
          "f33": "3.6.1-16",
          "f34": "3.6.1-17",
          "f35": "", 
          "rawhide": "3.6.1"
        },
        "latestVersion": "3.6.1",
        "opensuse": {
          "leap152": "3.6.1-l",
          "leap153": "3.6.1-l",
          "tumbleweed": "3.6.1-3.26"
        },
        "solus": "N/A",
        "ubuntu": {
          "bionic": "3.6.1-7",
          "focal": "3.6.1-9",
          "impish": "3.6.1-9",
          "mint": {
            "mint20": "",
            "mint19": ""
          },
          "neonversion": "N/A"
        },
        "updated": "Oct 16, 2021"
      }
    }
  ]
}